src/__init__.py
src/api/__init__.py
src/api/check.py
src/api/config.py
src/api/constants.py
src/api/dataref.py
src/api/debug.py
src/api/decorator.py
src/api/errmsg.py
src/api/exception.py
src/api/fp.py
src/api/global_.py
src/api/opcodestemps.py
src/api/optimize.py
src/api/options.py
src/api/python_version_check.py
src/api/string_labels.py
src/api/symboltable/__init__.py
src/api/symboltable/scope.py
src/api/symboltable/symboltable.py
src/api/tmp_labels.py
src/api/utils.py
src/arch/__init__.py
src/arch/interface/__init__.py
src/arch/interface/backend.py
src/arch/interface/optimizer.py
src/arch/interface/quad.py
src/arch/z80/__init__.py
src/arch/z80/backend/_16bit.py
src/arch/z80/backend/_32bit.py
src/arch/z80/backend/_8bit.py
src/arch/z80/backend/__init__.py
src/arch/z80/backend/_array.py
src/arch/z80/backend/_f16.py
src/arch/z80/backend/_float.py
src/arch/z80/backend/_parray.py
src/arch/z80/backend/_pload.py
src/arch/z80/backend/_str.py
src/arch/z80/backend/common.py
src/arch/z80/backend/exception.py
src/arch/z80/backend/generic.py
src/arch/z80/backend/icinfo.py
src/arch/z80/backend/icinstruction.py
src/arch/z80/backend/main.py
src/arch/z80/backend/py.typed
src/arch/z80/backend/quad.py
src/arch/z80/backend/runtime/__init__.py
src/arch/z80/backend/runtime/core.py
src/arch/z80/backend/runtime/datarestore.py
src/arch/z80/backend/runtime/io.py
src/arch/z80/backend/runtime/labels.py
src/arch/z80/backend/runtime/math.py
src/arch/z80/backend/runtime/misc.py
src/arch/z80/backend/runtime/namespace.py
src/arch/z80/backend/runtime/random.py
src/arch/z80/beep.py
src/arch/z80/optimizer/__init__.py
src/arch/z80/optimizer/asm.py
src/arch/z80/optimizer/basicblock.py
src/arch/z80/optimizer/cpustate.py
src/arch/z80/optimizer/errors.py
src/arch/z80/optimizer/flow_graph.py
src/arch/z80/optimizer/helpers.py
src/arch/z80/optimizer/labelinfo.py
src/arch/z80/optimizer/labels_dict.py
src/arch/z80/optimizer/main.py
src/arch/z80/optimizer/memcell.py
src/arch/z80/optimizer/patterns.py
zxbasic-1.18.4.dist-info/LICENSE.txt
zxbasic-1.18.4.dist-info/METADATA
zxbasic-1.18.4.dist-info/WHEEL
zxbasic-1.18.4.dist-info/entry_points.txt
zxbasic-1.18.4.dist-info/RECORD
