Metadata-Version: 2.1
Name: zxbasic
Version: 1.18.4
Summary: Boriel's ZX BASIC Compiler
Home-page: https://github.com/boriel-basic
License: AGPL-3.0-or-later
Keywords: compiler,zxspectrum,BASIC,z80
Author: Jose Rodriguez
Author-email: zxbasic@boriel.com
Requires-Python: >=3.11,<4.0
Classifier: Development Status :: 5 - Production/Stable
Classifier: Intended Audience :: Developers
Classifier: License :: OSI Approved :: GNU Affero General Public License v3
Classifier: License :: OSI Approved :: GNU Affero General Public License v3 or later (AGPLv3+)
Classifier: Programming Language :: Python :: 3
Classifier: Programming Language :: Python :: 3.11
Classifier: Programming Language :: Python :: 3.12
Classifier: Topic :: Software Development :: Build Tools
Project-URL: Documentation, https://zxbasic.readthedocs.io
Project-URL: Repository, https://github.com/boriel-basic/zxbasic
